autotau/__init__.py
autotau/examples.py
autotau/core/__init__.py
autotau/core/auto_tau_fitter.py
autotau/core/cycles_auto_tau_fitter.py
autotau/core/cycles_tau_fitter.py
autotau/core/parallel.py
autotau/core/parallel_cycles_tau_fitter.py
autotau/core/tau_fitter.py
autotau/core/window_finder.py
tests/__init__.py
tests/test_basic.py
autotau-0.4.5.dist-info/LICENSE
autotau-0.4.5.dist-info/METADATA
autotau-0.4.5.dist-info/WHEEL
autotau-0.4.5.dist-info/top_level.txt
autotau-0.4.5.dist-info/RECORD
