Metadata-Version: 2.2
Name: autotau
Version: 0.4.5
Summary: Automated time constant (tau) fitting tool with decoupled window search and manual fitting support
Home-page: https://github.com/Durian-Leader/autotau
Author: Donghao Li
Author-email: lidonghao100@outlook.com
Keywords: tau,fitting,exponential,signal processing,parallel,optimization,numba
Classifier: Development Status :: 3 - Alpha
Classifier: Intended Audience :: Science/Research
Classifier: Programming Language :: Python :: 3
Classifier: Programming Language :: Python :: 3.6
Classifier: Programming Language :: Python :: 3.7
Classifier: Programming Language :: Python :: 3.8
Classifier: Programming Language :: Python :: 3.9
Classifier: License :: OSI Approved :: MIT License
Classifier: Topic :: Scientific/Engineering
Requires-Python: >=3.6
License-File: LICENSE
Requires-Dist: numpy>=1.18.0
Requires-Dist: scipy>=1.4.0
Requires-Dist: matplotlib>=3.1.0
Requires-Dist: pandas>=1.0.0
Requires-Dist: tqdm>=4.45.0
Dynamic: author
Dynamic: author-email
Dynamic: classifier
Dynamic: description
Dynamic: description-content-type
Dynamic: home-page
Dynamic: keywords
Dynamic: requires-dist
Dynamic: requires-python
Dynamic: summary
